nidec-inventory/__init__.py
nidec-inventory/cli_parameters.py
nidec-inventory/nidec-inventory.py
nidec-inventory/helpers/__init__.py
nidec-inventory/helpers/file_helpers.py
nidec-inventory/nidec/__init__.py
nidec-inventory/nidec/drive_inventory.py
nidec-inventory/nidec/nidec_drive.py
nidec-inventory/nidec/nidec_param_file_engine.py
src/__init__.py
src/cli_parameters.py
src/helpers/__init__.py
src/helpers/file_helpers.py
src/nidec/__init__.py
src/nidec/drive_inventory.py
src/nidec/nidec_drive.py
src/nidec/nidec_param_file_engine.py
tests/__init__.py
nidecinventory-0.0.5.dist-info/LICENSE
nidecinventory-0.0.5.dist-info/METADATA
nidecinventory-0.0.5.dist-info/WHEEL
nidecinventory-0.0.5.dist-info/top_level.txt
nidecinventory-0.0.5.dist-info/RECORD
